podcli.py
podcli-1.0.1.dist-info/METADATA
podcli-1.0.1.dist-info/WHEEL
podcli-1.0.1.dist-info/entry_points.txt
podcli-1.0.1.dist-info/top_level.txt
podcli-1.0.1.dist-info/RECORD
