Metadata-Version: 2.4
Name: podcli
Version: 1.0.1
Summary: Terminal Based Podcast Client with search, subscription management, and playback
Author-email: Pawan Tikar <pawantikar08@gmail.com>
Keywords: podcast,cli,terminal,audio,rss
Requires-Python: >=3.7
Requires-Dist: requests
Requires-Dist: python-dotenv
Requires-Dist: tqdm
